<FileList>
  <File Reference="Telerik.Windows.Cloud.Controls.dll">
    <ToolboxItems UIFramework="WPF" VSCategory="Telerik UI for WPF - Cloud Upload NoXAML 2024 Q4 (NuGet)" BlendCategory="Telerik UI for WPF - Cloud Upload NoXAML 2024 Q4 (NuGet)">
      <Item Type="Telerik.Windows.Cloud.Controls.RadCloudUploadListItem" />
      <Item Type="Telerik.Windows.Cloud.Controls.RadCloudUpload" />
      <Item Type="Telerik.Windows.Cloud.Controls.RadCloudUploadList" />
    </ToolboxItems>
  </File>
  <File Reference="Telerik.Windows.Controls.Chart.dll">
    <ToolboxItems UIFramework="WPF" VSCategory="Telerik UI for WPF - Data Visualization NoXAML 2024 Q4 (NuGet)" BlendCategory="Telerik UI for WPF - Data Visualization NoXAML 2024 Q4 (NuGet)">
      <Item Type="Telerik.Windows.Controls.RadCartesianChart3D" />
      <Item Type="Telerik.Windows.Controls.ChartDataSource" />
      <Item Type="Telerik.Windows.Controls.RadFunnelChart" />
      <Item Type="Telerik.Windows.Controls.RadCartesianChart" />
      <Item Type="Telerik.Windows.Controls.RadPieChart" />
      <Item Type="Telerik.Windows.Controls.RadPolarChart" />
    </ToolboxItems>
  </File>
  <File Reference="Telerik.Windows.Controls.Charting.dll">
    <ToolboxItems UIFramework="WPF" VSCategory="Telerik UI for WPF - Data Visualization NoXAML 2024 Q4 (NuGet)" BlendCategory="Telerik UI for WPF - Data Visualization NoXAML 2024 Q4 (NuGet)">
      <Item Type="Telerik.Windows.Controls.RadChart" />
    </ToolboxItems>
  </File>
  <File Reference="Telerik.Windows.Controls.ConversationalUI.dll">
    <ToolboxItems UIFramework="WPF" VSCategory="Telerik UI for WPF - ConversationalUI NoXAML 2024 Q4 (NuGet)" BlendCategory="Telerik UI for WPF - ConversationalUI NoXAML 2024 Q4 (NuGet)">
      <Item Type="Telerik.Windows.Controls.RadAIPrompt" />
      <Item Type="Telerik.Windows.Controls.RadAIPromptButton" />
      <Item Type="Telerik.Windows.Controls.RadChat" />
    </ToolboxItems>
  </File>
  <File Reference="Telerik.Windows.Controls.Data.dll">
    <ToolboxItems UIFramework="WPF" VSCategory="Telerik UI for WPF - Data NoXAML 2024 Q4 (NuGet)" BlendCategory="Telerik UI for WPF - Data NoXAML 2024 Q4 (NuGet)">
      <Item Type="Telerik.Windows.Controls.RadCardView" />
      <Item Type="Telerik.Windows.Controls.RadCollectionNavigator" />
      <Item Type="Telerik.Windows.Controls.RadDataFilter" />
      <Item Type="Telerik.Windows.Controls.RadDataForm" />
      <Item Type="Telerik.Windows.Controls.RadDataPager" />
      <Item Type="Telerik.Windows.Controls.RadPropertyGrid" />
      <Item Type="Telerik.Windows.Controls.Data.PropertyGrid.CollectionEditor" />
      <Item Type="Telerik.Windows.Controls.Data.PropertyGrid.CollectionEditorPicker" />
    </ToolboxItems>
    <ToolboxItems UIFramework="WPF" VSCategory="Telerik UI for WPF - Input NoXAML 2024 Q4 (NuGet)" BlendCategory="Telerik UI for WPF - Input NoXAML 2024 Q4 (NuGet)">
      <Item Type="Telerik.Windows.Controls.DataFormCheckBoxField" />
      <Item Type="Telerik.Windows.Controls.DataFormComboBoxField" />
      <Item Type="Telerik.Windows.Controls.DataFormDataField" />
      <Item Type="Telerik.Windows.Controls.DataFormDateField" />
      <Item Type="Telerik.Windows.Controls.Data.PropertyGrid.FlagEnumEditor" />
    </ToolboxItems>
  </File>
  <File Reference="Telerik.Windows.Controls.DataServices.dll">
    <ToolboxItems UIFramework="WPF" VSCategory="Telerik UI for WPF - Data NoXAML 2024 Q4 (NuGet)" BlendCategory="Telerik UI for WPF - Data NoXAML 2024 Q4 (NuGet)">
      <Item Type="Telerik.Windows.Controls.RadDataServiceDataSource" />
    </ToolboxItems>
  </File>
  <File Reference="Telerik.Windows.Controls.DataVisualization.dll">
    <ToolboxItems UIFramework="WPF" VSCategory="Telerik UI for WPF - Data Visualization NoXAML 2024 Q4 (NuGet)" BlendCategory="Telerik UI for WPF - Data Visualization NoXAML 2024 Q4 (NuGet)">
      <Item Type="Telerik.Windows.Controls.RadBarcode" />
      <Item Type="Telerik.Windows.Controls.RadBarcodeReader" />
      <Item Type="Telerik.Windows.Controls.RadHorizontalBulletGraph" />
      <Item Type="Telerik.Windows.Controls.RadVerticalBulletGraph" />
      <Item Type="Telerik.Windows.Controls.RadHorizontalDataAxis" />
      <Item Type="Telerik.Windows.Controls.RadDataBar" />
      <Item Type="Telerik.Windows.Controls.RadStacked100DataBar" />
      <Item Type="Telerik.Windows.Controls.RadStackedDataBar" />
      <Item Type="Telerik.Windows.Controls.RadVerticalDataAxis" />
      <Item Type="Telerik.Windows.Controls.RadHorizontalLinearGauge" />
      <Item Type="Telerik.Windows.Controls.RadVerticalLinearGauge" />
      <Item Type="Telerik.Windows.Controls.RadQuadrantNEGauge" />
      <Item Type="Telerik.Windows.Controls.RadQuadrantNWGauge" />
      <Item Type="Telerik.Windows.Controls.RadQuadrantSEGauge" />
      <Item Type="Telerik.Windows.Controls.RadQuadrantSWGauge" />
      <Item Type="Telerik.Windows.Controls.RadRadialGauge" />
      <Item Type="Telerik.Windows.Controls.RadSemicircleEastGauge" />
      <Item Type="Telerik.Windows.Controls.RadSemicircleNorthGauge" />
      <Item Type="Telerik.Windows.Controls.RadSemicircleSouthGauge" />
      <Item Type="Telerik.Windows.Controls.RadSemicircleWestGauge" />
      <Item Type="Telerik.Windows.Controls.RadHeatMap" />
      <Item Type="Telerik.Windows.Controls.RadAreaSparkline" />
      <Item Type="Telerik.Windows.Controls.RadColumnSparkline" />
      <Item Type="Telerik.Windows.Controls.RadLinearSparkline" />
      <Item Type="Telerik.Windows.Controls.RadScatterSparkline" />
      <Item Type="Telerik.Windows.Controls.RadWinLossSparkline" />
      <Item Type="Telerik.Windows.Controls.RadTimeBar" />
      <Item Type="Telerik.Windows.Controls.RadTimeline" />
      <Item Type="Telerik.Windows.Controls.RadPivotMap" />
      <Item Type="Telerik.Windows.Controls.RadTreeMap" />
      <Item Type="Telerik.Windows.Controls.RadMap" />
    </ToolboxItems>
  </File>
  <File Reference="Telerik.Windows.Controls.Diagrams.dll">
    <ToolboxItems UIFramework="WPF" VSCategory="Telerik UI for WPF - Diagram NoXAML 2024 Q4 (NuGet)" BlendCategory="Telerik UI for WPF - Diagram NoXAML 2024 Q4 (NuGet)">
      <Item Type="Telerik.Windows.Controls.RadDiagram" />
      <Item Type="Telerik.Windows.Controls.RadDiagramConnection" />
      <Item Type="Telerik.Windows.Controls.RadDiagramContainerShape" />
      <Item Type="Telerik.Windows.Controls.RadDiagramShape" />
      <Item Type="Telerik.Windows.Controls.RadDiagramTextShape" />
    </ToolboxItems>
  </File>
  <File Reference="Telerik.Windows.Controls.Diagrams.Extensions.dll">
    <ToolboxItems UIFramework="WPF" VSCategory="Telerik UI for WPF - Diagram NoXAML 2024 Q4 (NuGet)" BlendCategory="Telerik UI for WPF - Diagram NoXAML 2024 Q4 (NuGet)">
      <Item Type="Telerik.Windows.Controls.Diagrams.Extensions.RadDiagramPrintPreview" />
      <Item Type="Telerik.Windows.Controls.Diagrams.Extensions.RadDiagramRuler" />
      <Item Type="Telerik.Windows.Controls.Diagrams.Extensions.SettingsPaneView" />
      <Item Type="Telerik.Windows.Controls.Diagrams.Extensions.SettingsPane" />
      <Item Type="Telerik.Windows.Controls.Diagrams.Extensions.RadDiagramThumbnail" />
      <Item Type="Telerik.Windows.Controls.Diagrams.Extensions.RadDiagramNavigationPane" />
      <Item Type="Telerik.Windows.Controls.Diagrams.Extensions.RadDiagramToolbox" />
      <Item Type="Telerik.Windows.Controls.Diagrams.Extensions.RadDiagramToolboxGroup" />
    </ToolboxItems>
  </File>
  <File Reference="Telerik.Windows.Controls.Diagrams.Ribbon.dll">
    <ToolboxItems UIFramework="WPF" VSCategory="Telerik UI for WPF - Diagram NoXAML 2024 Q4 (NuGet)" BlendCategory="Telerik UI for WPF - Diagram NoXAML 2024 Q4 (NuGet)">
      <Item Type="Telerik.Windows.Controls.Diagrams.Ribbon.RadDiagramRibbon" />
    </ToolboxItems>
  </File>
  <File Reference="Telerik.Windows.Controls.dll">
    <ToolboxItems UIFramework="WPF" VSCategory="Telerik UI for WPF - Common NoXAML 2024 Q4 (NuGet)" BlendCategory="Telerik UI for WPF - Common NoXAML 2024 Q4 (NuGet)">
      <Item Type="Telerik.Windows.Controls.RadBadge" />
      <Item Type="Telerik.Windows.Controls.RadCallout" />
      <Item Type="Telerik.Windows.Controls.RadHighlightTextBlock" />
      <Item Type="Telerik.Windows.Controls.RadSvgImage" />
      <Item Type="Telerik.Windows.Controls.Label" />
      <Item Type="Telerik.Windows.Controls.RadToolTip" />
      <Item Type="Telerik.Windows.Controls.RadToolTipContentView" />
    </ToolboxItems>
    <ToolboxItems UIFramework="WPF" VSCategory="Telerik UI for WPF - Data NoXAML 2024 Q4 (NuGet)" BlendCategory="Telerik UI for WPF - Data NoXAML 2024 Q4 (NuGet)">
      <Item Type="Telerik.Windows.Controls.RadCircularProgressBar" />
      <Item Type="Telerik.Windows.Controls.RadStepProgressBar" />
      <Item Type="Telerik.Windows.Controls.RadStepProgressBarItem" />
      <Item Type="Telerik.Windows.Controls.RadListBox" />
      <Item Type="Telerik.Windows.Controls.VirtualizingWrapPanel" />
      <Item Type="Telerik.Windows.Controls.RadListBoxItem" />
      <Item Type="Telerik.Windows.Controls.RadProgressBar" />
    </ToolboxItems>
    <ToolboxItems UIFramework="WPF" VSCategory="Telerik UI for WPF - Navigation NoXAML 2024 Q4 (NuGet)" BlendCategory="Telerik UI for WPF - Navigation NoXAML 2024 Q4 (NuGet)">
      <Item Type="Telerik.Windows.Controls.RadPipsPager" />
      <Item Type="Telerik.Windows.Controls.RadPipsPagerItem" />
      <Item Type="Telerik.Windows.Controls.RadSlideView" />
      <Item Type="Telerik.Windows.Controls.RadTaskBoard" />
      <Item Type="Telerik.Windows.Controls.RadTileList" />
      <Item Type="Telerik.Windows.Controls.Tile" />
    </ToolboxItems>
    <ToolboxItems UIFramework="WPF" VSCategory="Telerik UI for WPF - Input NoXAML 2024 Q4 (NuGet)" BlendCategory="Telerik UI for WPF - Input NoXAML 2024 Q4 (NuGet)">
      <Item Type="Telerik.Windows.Controls.RadWatermarkTextBox" />
      <Item Type="Telerik.Windows.Controls.RadSlider" />
      <Item Type="Telerik.Windows.Controls.RadPasswordBox" />
    </ToolboxItems>
    <ToolboxItems UIFramework="WPF" VSCategory="Telerik UI for WPF - Containers NoXAML 2024 Q4 (NuGet)" BlendCategory="Telerik UI for WPF - Containers NoXAML 2024 Q4 (NuGet)">
      <Item Type="Telerik.Windows.Controls.RadBusyIndicator" />
      <Item Type="Telerik.Windows.Controls.RadExpander" />
      <Item Type="Telerik.Windows.Controls.RadFluidContentControl" />
      <Item Type="Telerik.Windows.Controls.GroupBox" />
      <Item Type="Telerik.Windows.Controls.RadTransitionControl" />
    </ToolboxItems>
    <ToolboxItems UIFramework="WPF" VSCategory="Telerik UI for WPF - Buttons NoXAML 2024 Q4 (NuGet)" BlendCategory="Telerik UI for WPF - Buttons NoXAML 2024 Q4 (NuGet)">
      <Item Type="Telerik.Windows.Controls.RadButton" />
      <Item Type="Telerik.Windows.Controls.RadDropDownButton" />
      <Item Type="Telerik.Windows.Controls.RadHyperlinkButton" />
      <Item Type="Telerik.Windows.Controls.RadPathButton" />
      <Item Type="Telerik.Windows.Controls.RadRadioButton" />
      <Item Type="Telerik.Windows.Controls.RadSplitButton" />
      <Item Type="Telerik.Windows.Controls.RadToggleButton" />
      <Item Type="Telerik.Windows.Controls.RadToggleSwitchButton" />
    </ToolboxItems>
    <ToolboxItems UIFramework="WPF" VSCategory="Telerik UI for WPF - Data Visualization NoXAML 2024 Q4 (NuGet)" BlendCategory="Telerik UI for WPF - Data Visualization NoXAML 2024 Q4 (NuGet)">
      <Item Type="Telerik.Windows.Controls.RadLegend" />
      <Item Type="Telerik.Windows.Controls.Legend.LegendItemControl" />
    </ToolboxItems>
  </File>
  <File Reference="Telerik.Windows.Controls.Docking.dll">
    <ToolboxItems UIFramework="WPF" VSCategory="Telerik UI for WPF - Containers NoXAML 2024 Q4 (NuGet)" BlendCategory="Telerik UI for WPF - Containers NoXAML 2024 Q4 (NuGet)">
      <Item Type="Telerik.Windows.Controls.RadDocking" />
      <Item Type="Telerik.Windows.Controls.RadDocumentPane" />
      <Item Type="Telerik.Windows.Controls.RadPane" />
      <Item Type="Telerik.Windows.Controls.RadPaneGroup" />
      <Item Type="Telerik.Windows.Controls.RadSplitContainer" />
    </ToolboxItems>
  </File>
  <File Reference="Telerik.Windows.Controls.EntityFrameworkCore.dll">
    <ToolboxItems UIFramework="WPF" VSCategory="Telerik UI for WPF - Data NoXAML 2024 Q4 (NuGet)" BlendCategory="Telerik UI for WPF - Data NoXAML 2024 Q4 (NuGet)">
      <Item Type="Telerik.Windows.Controls.RadEntityFrameworkCoreDataSource" />
    </ToolboxItems>
  </File>
  <File Reference="Telerik.Windows.Controls.Expressions.dll">
    <ToolboxItems UIFramework="WPF" VSCategory="Telerik UI for WPF - Data NoXAML 2024 Q4 (NuGet)" BlendCategory="Telerik UI for WPF - Data NoXAML 2024 Q4 (NuGet)">
      <Item Type="Telerik.Windows.Controls.RadExpressionEditor" />
    </ToolboxItems>
  </File>
  <File Reference="Telerik.Windows.Controls.FileDialogs.dll">
    <ToolboxItems UIFramework="WPF" VSCategory="Telerik UI for WPF - File Dialogs NoXAML 2024 Q4 (NuGet)" BlendCategory="Telerik UI for WPF - File Dialogs NoXAML 2024 Q4 (NuGet)">
      <Item Type="Telerik.Windows.Controls.RadOpenFileDialog" />
      <Item Type="Telerik.Windows.Controls.RadSaveFileDialog" />
      <Item Type="Telerik.Windows.Controls.RadFilePathPicker" />
      <Item Type="Telerik.Windows.Controls.RadOpenFolderDialog" />
      <Item Type="Telerik.Windows.Controls.FileDialogs.ExplorerControl" />
    </ToolboxItems>
  </File>
  <File Reference="Telerik.Windows.Controls.FixedDocumentViewers.dll">
    <ToolboxItems UIFramework="WPF" VSCategory="Telerik UI for WPF - Documents NoXAML 2024 Q4 (NuGet)" BlendCategory="Telerik UI for WPF - Documents NoXAML 2024 Q4 (NuGet)">
      <Item Type="Telerik.Windows.Controls.RadPdfViewer" />
    </ToolboxItems>
  </File>
  <File Reference="Telerik.Windows.Controls.FixedDocumentViewersUI.dll">
    <ToolboxItems UIFramework="WPF" VSCategory="Telerik UI for WPF - Documents NoXAML 2024 Q4 (NuGet)" BlendCategory="Telerik UI for WPF - Documents NoXAML 2024 Q4 (NuGet)">
      <Item Type="Telerik.Windows.Controls.RadPdfViewerToolBar" />
      <Item Type="Telerik.Windows.Controls.FixedDocumentViewersUI.RadPdfViewerNavigationPane" />
      <Item Type="Telerik.Windows.Controls.FixedDocumentViewersUI.SignaturePanel" />
    </ToolboxItems>
  </File>
  <File Reference="Telerik.Windows.Controls.GanttView.dll">
    <ToolboxItems UIFramework="WPF" VSCategory="Telerik UI for WPF - Data NoXAML 2024 Q4 (NuGet)" BlendCategory="Telerik UI for WPF - Data NoXAML 2024 Q4 (NuGet)">
      <Item Type="Telerik.Windows.Controls.RadGanttView" />
    </ToolboxItems>
  </File>
  <File Reference="Telerik.Windows.Controls.GridView.dll">
    <ToolboxItems UIFramework="WPF" VSCategory="Telerik UI for WPF - Data NoXAML 2024 Q4 (NuGet)" BlendCategory="Telerik UI for WPF - Data NoXAML 2024 Q4 (NuGet)">
      <Item Type="Telerik.Windows.Controls.RadGridView" />
      <Item Type="Telerik.Windows.Controls.RadMultiColumnComboBox" />
      <Item Type="Telerik.Windows.Controls.RadTreeListView" />
    </ToolboxItems>
  </File>
  <File Reference="Telerik.Windows.Controls.ImageEditor.dll">
    <ToolboxItems UIFramework="WPF" VSCategory="Telerik UI for WPF - Input NoXAML 2024 Q4 (NuGet)" BlendCategory="Telerik UI for WPF - Input NoXAML 2024 Q4 (NuGet)">
      <Item Type="Telerik.Windows.Controls.RadImageEditor" />
      <Item Type="Telerik.Windows.Controls.RadImageEditorUI" />
    </ToolboxItems>
  </File>
  <File Reference="Telerik.Windows.Controls.Input.dll">
    <ToolboxItems UIFramework="WPF" VSCategory="Telerik UI for WPF - Input NoXAML 2024 Q4 (NuGet)" BlendCategory="Telerik UI for WPF - Input NoXAML 2024 Q4 (NuGet)">
      <Item Type="Telerik.Windows.Controls.RadAutoCompleteBox" />
      <Item Type="Telerik.Windows.Controls.RadAutoCompleteBoxItem" />
      <Item Type="Telerik.Windows.Controls.RadAutoSuggestBox" />
      <Item Type="Telerik.Windows.Controls.RadCalculator" />
      <Item Type="Telerik.Windows.Controls.RadCalculatorPicker" />
      <Item Type="Telerik.Windows.Controls.RadCalendar" />
      <Item Type="Telerik.Windows.Controls.RadColorEditor" />
      <Item Type="Telerik.Windows.Controls.RadColorPicker" />
      <Item Type="Telerik.Windows.Controls.RadColorSelector" />
      <Item Type="Telerik.Windows.Controls.RadComboBox" />
      <Item Type="Telerik.Windows.Controls.RadComboBoxItem" />
      <Item Type="Telerik.Windows.Controls.RadDatePicker" />
      <Item Type="Telerik.Windows.Controls.RadDateRangePicker" />
      <Item Type="Telerik.Windows.Controls.RadDateTimePicker" />
      <Item Type="Telerik.Windows.Controls.RadMaskedCurrencyInput" />
      <Item Type="Telerik.Windows.Controls.RadMaskedDateTimeInput" />
      <Item Type="Telerik.Windows.Controls.RadMaskedNumericInput" />
      <Item Type="Telerik.Windows.Controls.RadMaskedTextInput" />
      <Item Type="Telerik.Windows.Controls.RadNumericUpDown" />
      <Item Type="Telerik.Windows.Controls.RadRating" />
      <Item Type="Telerik.Windows.Controls.RadRatingItem" />
      <Item Type="Telerik.Windows.Controls.RadTimePicker" />
      <Item Type="Telerik.Windows.Controls.RadTimeSpanPicker" />
    </ToolboxItems>
  </File>
  <File Reference="Telerik.Windows.Controls.Media.dll">
    <ToolboxItems UIFramework="WPF" VSCategory="Telerik UI for WPF - Media NoXAML 2024 Q4 (NuGet)" BlendCategory="Telerik UI for WPF - Media NoXAML 2024 Q4 (NuGet)">
      <Item Type="Telerik.Windows.Controls.CameraSettingsControl" />
      <Item Type="Telerik.Windows.Controls.RadWebCam" />
    </ToolboxItems>
  </File>
  <File Reference="Telerik.Windows.Controls.Navigation.dll">
    <ToolboxItems UIFramework="WPF" VSCategory="Telerik UI for WPF - Navigation NoXAML 2024 Q4 (NuGet)" BlendCategory="Telerik UI for WPF - Navigation NoXAML 2024 Q4 (NuGet)">
      <Item Type="Telerik.Windows.Controls.RadCarouselPanel" />
      <Item Type="Telerik.Windows.Controls.RadMenu" />
      <Item Type="Telerik.Windows.Controls.RadNavigationView" />
      <Item Type="Telerik.Windows.Controls.RadNavigationViewItem" />
      <Item Type="Telerik.Windows.Controls.RadOfficeNavigationBar" />
      <Item Type="Telerik.Windows.Controls.RadOfficeNavigationBarItem" />
      <Item Type="Telerik.Windows.Controls.RadTabbedWindow" />
      <Item Type="Telerik.Windows.Controls.RadTabControl" />
      <Item Type="Telerik.Windows.Controls.RadBreadcrumb" />
      <Item Type="Telerik.Windows.Controls.RadBreadcrumbItem" />
      <Item Type="Telerik.Windows.Controls.RadCarousel" />
      <Item Type="Telerik.Windows.Controls.RadContextMenu" />
      <Item Type="Telerik.Windows.Controls.RadMenuSeparatorItem" />
      <Item Type="Telerik.Windows.Controls.RadMenuGroupItem" />
      <Item Type="Telerik.Windows.Controls.RadMenuItem" />
      <Item Type="Telerik.Windows.Controls.RadOutlookBar" />
      <Item Type="Telerik.Windows.Controls.RadPanelBar" />
      <Item Type="Telerik.Windows.Controls.RadPanelBarItem" />
      <Item Type="Telerik.Windows.Controls.RadRadialMenuItem" />
      <Item Type="Telerik.Windows.Controls.RadRadialMenu" />
      <Item Type="Telerik.Windows.Controls.RadVirtualKeyboard" />
      <Item Type="Telerik.Windows.Controls.RadWizard" />
      <Item Type="Telerik.Windows.Controls.CompletionWizardPage" />
      <Item Type="Telerik.Windows.Controls.WelcomeWizardPage" />
      <Item Type="Telerik.Windows.Controls.WizardPage" />
      <Item Type="Telerik.Windows.Controls.RadTabItem" />
      <Item Type="Telerik.Windows.Controls.RadOutlookBarItem" />
      <Item Type="Telerik.Windows.Controls.RadToolBar" />
      <Item Type="Telerik.Windows.Controls.RadToolBarSeparator" />
      <Item Type="Telerik.Windows.Controls.RadToolBarTray" />
      <Item Type="Telerik.Windows.Controls.RadTreeView" />
      <Item Type="Telerik.Windows.Controls.RadTreeViewItem" />
      <Item Type="Telerik.Windows.Controls.CarouselItem" />
      <Item Type="Telerik.Windows.Controls.RadAlert" />
      <Item Type="Telerik.Windows.Controls.RadConfirm" />
      <Item Type="Telerik.Windows.Controls.RadPrompt" />
    </ToolboxItems>
    <ToolboxItems UIFramework="WPF" VSCategory="Telerik UI for WPF - Containers NoXAML 2024 Q4 (NuGet)" BlendCategory="Telerik UI for WPF - Containers NoXAML 2024 Q4 (NuGet)">
      <Item Type="Telerik.Windows.Controls.LayoutControlExpanderGroup" />
      <Item Type="Telerik.Windows.Controls.LayoutControlTabGroupItem" />
      <Item Type="Telerik.Windows.Controls.LayoutControlTabGroup" />
      <Item Type="Telerik.Windows.Controls.RadLayoutControl" />
      <Item Type="Telerik.Windows.Controls.RadNotifyIcon" />
      <Item Type="Telerik.Windows.Controls.RadSplashScreen" />
      <Item Type="Telerik.Windows.Controls.RadBook" />
      <Item Type="Telerik.Windows.Controls.RadBookItem" />
      <Item Type="Telerik.Windows.Controls.RadDesktopAlert" />
      <Item Type="Telerik.Windows.Controls.LayoutControlGroup" />
      <Item Type="Telerik.Windows.Controls.RadTileView" />
      <Item Type="Telerik.Windows.Controls.RadTileViewItem" />
      <Item Type="Telerik.Windows.Controls.RadWindow" />
      <Item Type="Telerik.Windows.Controls.LayoutControl.LayoutControlSplitter" />
      <Item Type="Telerik.Windows.Controls.LayoutControl.LayoutControlToolBox" />
      <Item Type="Telerik.Windows.Controls.LayoutControl.LayoutControlToolBoxView" />
    </ToolboxItems>
  </File>
  <File Reference="Telerik.Windows.Controls.Pivot.dll">
    <ToolboxItems UIFramework="WPF" VSCategory="Telerik UI for WPF - Data NoXAML 2024 Q4 (NuGet)" BlendCategory="Telerik UI for WPF - Data NoXAML 2024 Q4 (NuGet)">
      <Item Type="Telerik.Windows.Controls.RadPivotGrid" />
    </ToolboxItems>
  </File>
  <File Reference="Telerik.Windows.Controls.PivotFieldList.dll">
    <ToolboxItems UIFramework="WPF" VSCategory="Telerik UI for WPF - Data NoXAML 2024 Q4 (NuGet)" BlendCategory="Telerik UI for WPF - Data NoXAML 2024 Q4 (NuGet)">
      <Item Type="Telerik.Windows.Controls.RadPivotFieldList" />
    </ToolboxItems>
  </File>
  <File Reference="Telerik.Windows.Controls.RibbonView.dll">
    <ToolboxItems UIFramework="WPF" VSCategory="Telerik UI for WPF - Navigation NoXAML 2024 Q4 (NuGet)" BlendCategory="Telerik UI for WPF - Navigation NoXAML 2024 Q4 (NuGet)">
      <Item Type="Telerik.Windows.Controls.ApplicationMenu" />
      <Item Type="Telerik.Windows.Controls.RadRibbonSplitButton" />
      <Item Type="Telerik.Windows.Controls.RadRibbonButton" />
      <Item Type="Telerik.Windows.Controls.RadRibbonDropDownButton" />
      <Item Type="Telerik.Windows.Controls.RadRibbonRadioButton" />
      <Item Type="Telerik.Windows.Controls.RadRibbonToggleButton" />
      <Item Type="Telerik.Windows.Controls.RadRibbonTab" />
      <Item Type="Telerik.Windows.Controls.RadRibbonView" />
      <Item Type="Telerik.Windows.Controls.QuickAccessToolBar" />
      <Item Type="Telerik.Windows.Controls.RadButtonGroup" />
      <Item Type="Telerik.Windows.Controls.RadCollapsiblePanel" />
      <Item Type="Telerik.Windows.Controls.RadGalleryItem" />
      <Item Type="Telerik.Windows.Controls.RadOrderedWrapPanel" />
      <Item Type="Telerik.Windows.Controls.RadRibbonBackstage" />
      <Item Type="Telerik.Windows.Controls.RadRibbonBackstageItem" />
      <Item Type="Telerik.Windows.Controls.RadRibbonComboBox" />
      <Item Type="Telerik.Windows.Controls.RadRibbonComboBoxItem" />
      <Item Type="Telerik.Windows.Controls.RadRibbonContextualGroup" />
      <Item Type="Telerik.Windows.Controls.RadRibbonGallery" />
      <Item Type="Telerik.Windows.Controls.RadRibbonGroup" />
    </ToolboxItems>
  </File>
  <File Reference="Telerik.Windows.Controls.RichTextBox.dll">
    <ToolboxItems UIFramework="WPF" VSCategory="Telerik UI for WPF - Documents NoXAML 2024 Q4 (NuGet)" BlendCategory="Telerik UI for WPF - Documents NoXAML 2024 Q4 (NuGet)">
      <Item Type="Telerik.Windows.Controls.RadRichTextBox" />
      <Item Type="Telerik.Windows.Controls.RichTextBoxUI.RadRichTextBoxRibbonUI" />
      <Item Type="Telerik.Windows.Controls.RichTextBoxUI.DocumentRuler" />
      <Item Type="Telerik.Windows.Controls.RichTextBoxUI.RadRichTextBoxStatusBar" />
    </ToolboxItems>
  </File>
  <File Reference="Telerik.Windows.Controls.ScheduleView.dll">
    <ToolboxItems UIFramework="WPF" VSCategory="Telerik UI for WPF - Data NoXAML 2024 Q4 (NuGet)" BlendCategory="Telerik UI for WPF - Data NoXAML 2024 Q4 (NuGet)">
      <Item Type="Telerik.Windows.Controls.RadScheduleView" />
    </ToolboxItems>
  </File>
  <File Reference="Telerik.Windows.Controls.Spreadsheet.dll">
    <ToolboxItems UIFramework="WPF" VSCategory="Telerik UI for WPF - Documents NoXAML 2024 Q4 (NuGet)" BlendCategory="Telerik UI for WPF - Documents NoXAML 2024 Q4 (NuGet)">
      <Item Type="Telerik.Windows.Controls.RadSpreadsheet" />
      <Item Type="Telerik.Windows.Controls.Spreadsheet.Controls.RadSpreadsheetFormulaBar" />
      <Item Type="Telerik.Windows.Controls.Spreadsheet.Controls.RadSpreadsheetStatusBar" />
    </ToolboxItems>
  </File>
  <File Reference="Telerik.Windows.Controls.SpreadsheetUI.dll">
    <ToolboxItems UIFramework="WPF" VSCategory="Telerik UI for WPF - Documents NoXAML 2024 Q4 (NuGet)" BlendCategory="Telerik UI for WPF - Documents NoXAML 2024 Q4 (NuGet)">
      <Item Type="Telerik.Windows.Controls.RadSpreadsheetRibbon" />
    </ToolboxItems>
  </File>
  <File Reference="Telerik.Windows.Controls.SyntaxEditor.dll">
    <ToolboxItems UIFramework="WPF" VSCategory="Telerik UI for WPF - Input NoXAML 2024 Q4 (NuGet)" BlendCategory="Telerik UI for WPF - Input NoXAML 2024 Q4 (NuGet)">
      <Item Type="Telerik.Windows.Controls.RadSyntaxEditor" />
    </ToolboxItems>
  </File>
  <File Reference="Telerik.Windows.Controls.VirtualGrid.dll">
    <ToolboxItems UIFramework="WPF" VSCategory="Telerik UI for WPF - Data NoXAML 2024 Q4 (NuGet)" BlendCategory="Telerik UI for WPF - Data NoXAML 2024 Q4 (NuGet)">
      <Item Type="Telerik.Windows.Controls.RadVirtualGrid" />
    </ToolboxItems>
  </File>
</FileList>